sklearnpy/__init__.py
sklearnpy/classify.py
sklearnpy/corrcoef.py
sklearnpy/example.py
sklearnpy/help_h.py
sklearnpy/k_means.py
sklearnpy/labels.py
sklearnpy/linear_predict.py
sklearnpy/pca.py
sklearnpy/vals_vectors.py
sklearnpy-1.0.0.dist-info/METADATA
sklearnpy-1.0.0.dist-info/WHEEL
sklearnpy-1.0.0.dist-info/licenses/LICENSE
sklearnpy-1.0.0.dist-info/RECORD
